{"AipFeZ0IVttGwiroks7fNQ==":"mbr-121x138.png","ZnifaJAhkJaJDOn8OTpD9A==":"mbr-1920x1280.jpg","lxIKqJUdo0yG0PzH+2GFOw==":"team-1564x962.jpg","GVA46l0xcuIJKwB/W6i7yg==":"wochenblatt-1916x1373.jpg","oY5HJVHHCzOA1omC1iGLJA==":"oliver%20junghardt,%20agnes%20konrad%20mit%20b%C3%BCrgermeisterin%20klara%20sch%C3%B6mig-1288x1717.jpg","deo+1QnHIf4G4Q8jtTauBQ==":"verkaufstheke%201-1288x966.jpg","y5EMT8F+gsgo7z/UNXiWxQ==":"verkaufstheke%202-1288x966.jpg","LioXLLKGpmFPEdRplXrkkw==":"hei%C3%9Ftheke-1288x966.jpg"}